git_commit_simplifier/__init__.py
git_commit_simplifier/__main__.py
git_commit_simplifier/cli.py
git_commit_simplifier/config.py
git_commit_simplifier/conventional.py
git_commit_simplifier/interactive.py
git_commit_simplifier-0.1.6.dist-info/LICENSE
git_commit_simplifier-0.1.6.dist-info/METADATA
git_commit_simplifier-0.1.6.dist-info/WHEEL
git_commit_simplifier-0.1.6.dist-info/entry_points.txt
git_commit_simplifier-0.1.6.dist-info/RECORD
