Metadata-Version: 2.3
Name: git-commit-simplifier
Version: 0.1.6
Summary: A tool to simplify Git commit message creation by analyzing changes
License: MIT
Keywords: git,commit,message,automation,developer-tools
Author: Christopher Dato
Author-email: christopherdato08@gmail.com
Requires-Python: >=3.8,<4.0
Classifier: Development Status :: 3 - Alpha
Classifier: Intended Audience :: Developers
Classifier: License :: OSI Approved :: MIT License
Classifier: Operating System :: OS Independent
Classifier: Programming Language :: Python :: 3
Classifier: Programming Language :: Python :: 3.8
Classifier: Programming Language :: Python :: 3.9
Classifier: Programming Language :: Python :: 3.10
Classifier: Programming Language :: Python :: 3.11
Classifier: Programming Language :: Python :: 3.12
Classifier: Programming Language :: Python :: 3.13
Classifier: Topic :: Software Development :: Version Control :: Git
Requires-Dist: click (>=8.1.7,<9.0.0)
Requires-Dist: colorama (>=0.4.6,<0.5.0)
Requires-Dist: gitpython (>=3.1.40,<4.0.0)
Requires-Dist: prompt_toolkit (>=3.0.36,<4.0.0)
Project-URL: Repository, https://github.com/Chris000888/git-commit-simplifier
